anom/__init__.py
anom/adapter.py
anom/conditions.py
anom/model.py
anom/namespaces.py
anom/properties.py
anom/query.py
anom/transaction.py
anom/adapters/__init__.py
anom/adapters/datastore_adapter.py
anom/adapters/memcache_adapter.py
anom/testing/__init__.py
anom/testing/emulator.py
anom-0.9.1.dist-info/DESCRIPTION.rst
anom-0.9.1.dist-info/METADATA
anom-0.9.1.dist-info/RECORD
anom-0.9.1.dist-info/WHEEL
anom-0.9.1.dist-info/metadata.json
anom-0.9.1.dist-info/top_level.txt
