Metadata-Version: 2.0
Name: anom
Version: 0.9.1
Summary: anom is an object mapper for Google Cloud Datastore.
Home-page: https://github.com/Bogdanp/anom-py
Author: Bogdan Popa
Author-email: popa.bogdanp@gmail.com
License: UNKNOWN
Platform: UNKNOWN
Provides-Extra: memcache
Requires-Dist: google-cloud-datastore (<2,>=1.7)
Requires-Dist: gcloud-requests (<3,>=2)
Requires-Dist: msgpack-python (<0.5,>=0.4)
Requires-Dist: python-dateutil (<3,>=2.6)
Provides-Extra: memcache
Requires-Dist: pylibmc (==1.5.2); extra == 'memcache'
